{
	"classes": [
		{
			"id": 101,
			"title": "Math",
			"created_at": "2022-08-10T14:38:18.614Z",
			"updated_at": "2022-08-10T14:38:18.614Z"
		},
		{
			"id": 102,
			"title": "Music",
			"created_at": "2022-08-10T14:38:18.614Z",
			"updated_at": "2022-08-10T14:38:18.614Z"
		},
		{
			"id": 103,
			"title": "IT",
			"created_at": "2022-08-10T14:38:18.614Z",
			"updated_at": "2022-08-10T14:38:18.614Z"
		},
		{
			"id": 104,
			"title": "English",
			"created_at": "2022-08-10T14:42:55.088Z"
		},
		{
			"id": "123",
			"title": "usic go",
			"created_at": "2022-08-12T14:18:11.521Z"
		}
	],
	"students": [
		{
			"id": 1,
			"name": "John Doe",
			"email": "john.doe@example.com",
			"created_at": "2022-08-10T14:38:18.614Z",
			"updated_at": "2022-08-10T14:38:18.614Z"
		},
		{
			"id": 2,
			"name": "Steve Jobs",
			"email": "steve.jobs@example.com",
			"created_at": "2022-08-10T14:38:18.614Z",
			"updated_at": "2022-08-10T14:38:18.614Z"
		},
		{
			"id": 3,
			"name": "Bill Gates",
			"email": "bill.gates@example.com",
			"created_at": "2022-08-10T14:38:18.614Z",
			"updated_at": "2022-08-10T14:38:18.614Z"
		},
		{
			"id": "13",
			"name": "asdasd",
			"email": "asdasd",
			"created_at": "2022-08-12T14:07:44.403Z"
		},
		{
			"id": "123",
			"name": "asdasd",
			"email": "asdasd",
			"created_at": "2022-08-12T14:08:06.406Z"
		},
		{
			"id": "123123",
			"name": "123123123",
			"email": "123123",
			"created_at": "2022-08-12T14:09:06.310Z"
		},
		{
			"id": "12312",
			"name": "123123123",
			"email": "123123",
			"created_at": "2022-08-12T14:09:22.259Z"
		},
		{
			"id": "123321",
			"name": "lalks;dk;alsd",
			"email": "adfasdasd",
			"created_at": "2022-08-12T14:14:06.758Z"
		},
		{
			"id": "12332231",
			"name": "lalks;dk;alsd",
			"email": "adfasdasd",
			"created_at": "2022-08-12T14:14:09.069Z"
		}
	],
	"student_classes": [
		{
			"student_id": 1,
			"class_id": 102,
			"joined_at": "2022-08-10T14:38:18.614Z"
		},
		{
			"student_id": 1,
			"class_id": 101,
			"joined_at": "2022-08-10T14:38:18.614Z"
		},
		{
			"student_id": 3,
			"class_id": 103,
			"joined_at": "2022-08-10T14:38:18.614Z"
		},
		{
			"student_id": 2,
			"class_id": 103,
			"joined_at": "2022-08-12T14:44:41.342Z"
		},
		{
			"student_id": 1,
			"class_id": 103,
			"joined_at": "2022-08-12T14:44:47.104Z"
		}
	]
}